pyorange/__init__.py
pyorange/anomaly.py
pyorange/arules.py
pyorange/classification.py
pyorange/clustering.py
pyorange/datasets.py
pyorange/nlp.py
pyorange/regression.py
pyorange/utils.py
pyorange-2.1.0.dist-info/LICENCE.txt
pyorange-2.1.0.dist-info/METADATA
pyorange-2.1.0.dist-info/WHEEL
pyorange-2.1.0.dist-info/top_level.txt
pyorange-2.1.0.dist-info/RECORD
