Metadata-Version: 2.1
Name: pyorange
Version: 2.1.0
Summary: PyOrange - An open source, low-code machine learning library in Python.
Home-page: https://github.com/pyspyder/pyorange
Author: satish kumar
Author-email: satishsriram369@gmail.com
License: MIT
Platform: UNKNOWN
Classifier: License :: OSI Approved :: MIT License
Classifier: Programming Language :: Python :: 3.6
Classifier: Programming Language :: Python :: 3.7
Classifier: Programming Language :: Python :: 3.8
License-File: LICENCE.txt
Requires-Dist: pycaret (==2.3.5)
Requires-Dist: vaderSentiment (==3.3.2)
Requires-Dist: multi-rake (==0.0.1)
Requires-Dist: langid (==1.1.6)
